{
    "Big rect. left main": [
        {
            "x": 0.0030416817571672114,
            "y": 0.4054393220226098
        },
        {
            "x": 0.1140785321879251,
            "y": 0.331698928442457
        },
        {
            "x": 0.059222114168643834,
            "y": 0.3687064008676587
        }
    ],
    "Circle central": [
        {
            "x": 0.9388712429358813,
            "y": 0.6396555346248335
        },
        {
            "x": 0.9358234726302423,
            "y": 0.6937171309896963
        },
        {
            "x": 0.9620957052262212,
            "y": 0.6137024648005592
        },
        {
            "x": 0.9980049905623943,
            "y": 0.7611348940967924
        },
        {
            "x": 0.9313745798527178,
            "y": 0.6633878303720231
        },
        {
            "x": 0.9974165580629353,
            "y": 0.592756730147976
        },
        {
            "x": 0.9573633588736569,
            "y": 0.7257380788149386
        },
        {
            "x": 0.9749216462340028,
            "y": 0.7425990919788772
        }
    ],
    "Side line top": [
        {
            "x": 0.9925142665106407,
            "y": 0.2601089975539792
        },
        {
            "x": 0.42071766659902066,
            "y": 0.23407937035943768
        },
        {
            "x": 0.0033078289109193452,
            "y": 0.20126111915937805
        },
        {
            "x": 0.8308857107434183,
            "y": 0.2558816689539925
        },
        {
            "x": 0.15055909818848068,
            "y": 0.21414576374599378
        },
        {
            "x": 0.2738758109624907,
            "y": 0.2236335655531228
        },
        {
            "x": 0.5537642819053541,
            "y": 0.2425453550740369
        },
        {
            "x": 0.6975914489791015,
            "y": 0.24902129073501741
        }
    ],
    "Big rect. left top": [
        {
            "x": 0.0026045999947677465,
            "y": 0.31748614544904896
        },
        {
            "x": 0.054077019485948195,
            "y": 0.3216519641385144
        },
        {
            "x": 0.10943238960052615,
            "y": 0.32562160361915904
        }
    ]
}