{
    "Side line right": [
        {
            "x": 0.9221176173236759,
            "y": 0.3429937044951713
        },
        {
            "x": 0.9861050555362837,
            "y": 0.6240313822363942
        },
        {
            "x": 0.9376666425179321,
            "y": 0.41527783770497684
        },
        {
            "x": 0.9598153083514626,
            "y": 0.5095798904799795
        }
    ],
    "Big rect. right top": [
        {
            "x": 0.0028335650403680003,
            "y": 0.4614962887349118
        },
        {
            "x": 0.9356650834930638,
            "y": 0.4534742739604882
        },
        {
            "x": 0.6495734710429333,
            "y": 0.4538092546383615
        },
        {
            "x": 0.1780188351548637,
            "y": 0.4600526210701775
        },
        {
            "x": 0.4532656549876463,
            "y": 0.4558407294777967
        }
    ],
    "Small rect. right main": [
        {
            "x": 0.23847250497986516,
            "y": 0.595585881559149
        },
        {
            "x": 0.004498047642366576,
            "y": 0.9348435732760524
        },
        {
            "x": 0.19571842141800475,
            "y": 0.6590661056409978
        },
        {
            "x": 0.11018216729261664,
            "y": 0.7784734432562074
        }
    ],
    "Small rect. right top": [
        {
            "x": 0.9611402182081967,
            "y": 0.5811729972167577
        },
        {
            "x": 0.2521953973840656,
            "y": 0.5893559735987759
        },
        {
            "x": 0.46025997317530754,
            "y": 0.585382189796455
        },
        {
            "x": 0.7039591149531056,
            "y": 0.5833744531196161
        }
    ],
    "Goal right post left": [
        {
            "x": 0.9936937402965007,
            "y": 0.6527593992774484
        },
        {
            "x": 0.9914444534023129,
            "y": 0.02209963631924145
        }
    ],
    "Small rect. right bottom": [
        {
            "x": 0.005407434234963933,
            "y": 0.9667042233234653
        },
        {
            "x": 0.995708329554076,
            "y": 0.9616392121122274
        },
        {
            "x": 0.3536636489298452,
            "y": 0.9596903402856478
        },
        {
            "x": 0.6551222594542748,
            "y": 0.9582960181453837
        }
    ]
}