{
    "Big rect. left main": [
        {
            "x": 0.9974299773634249,
            "y": 0.5886505907680055
        },
        {
            "x": 0.36566617544861196,
            "y": 0.8581719813285251
        },
        {
            "x": 0.4651856173676208,
            "y": 0.8138467254468327
        },
        {
            "x": 0.5816716616080655,
            "y": 0.7631780068156677
        },
        {
            "x": 0.6842965730950447,
            "y": 0.7191913634927731
        },
        {
            "x": 0.8053642630815102,
            "y": 0.6675346222492091
        },
        {
            "x": 0.9079611876950027,
            "y": 0.6248765575005896
        }
    ],
    "Goal left post right": [
        {
            "x": 0.422466320978259,
            "y": 0.4083466255035881
        },
        {
            "x": 0.42103433549666214,
            "y": 0.30608961435204124
        }
    ],
    "Small rect. left main": [
        {
            "x": 0.7319696538208282,
            "y": 0.464438007439031
        },
        {
            "x": 0.2652345170400868,
            "y": 0.6199935597283567
        },
        {
            "x": 0.35274334391730955,
            "y": 0.5912429394775695
        },
        {
            "x": 0.4780619817349797,
            "y": 0.5511524357041995
        },
        {
            "x": 0.583746099189848,
            "y": 0.5152022853033753
        },
        {
            "x": 0.654775397752387,
            "y": 0.49141903944676657
        }
    ],
    "Side line left": [
        {
            "x": 0.0014708221119101926,
            "y": 0.6068910500365835
        },
        {
            "x": 0.9978783371903583,
            "y": 0.3035574095501992
        },
        {
            "x": 0.12254938723667358,
            "y": 0.5704895430020296
        },
        {
            "x": 0.25068633134210316,
            "y": 0.5319852427432804
        },
        {
            "x": 0.3527601846165278,
            "y": 0.4998138352595913
        },
        {
            "x": 0.4610518852540654,
            "y": 0.46904247443720104
        },
        {
            "x": 0.5694370880672096,
            "y": 0.43632761310519763
        },
        {
            "x": 0.6660857266930985,
            "y": 0.4073209043996716
        },
        {
            "x": 0.7649433070245681,
            "y": 0.37670447925828576
        },
        {
            "x": 0.8701254238327132,
            "y": 0.344011874205125
        },
        {
            "x": 0.9395816714582773,
            "y": 0.3223295643044068
        }
    ],
    "Circle left": [
        {
            "x": 0.9983483321212616,
            "y": 0.6596627490660205
        },
        {
            "x": 0.7956748424282046,
            "y": 0.6758961017116767
        },
        {
            "x": 0.8533399051636134,
            "y": 0.673890438702159
        },
        {
            "x": 0.9179286601639295,
            "y": 0.668972291137553
        },
        {
            "x": 0.9609479978722844,
            "y": 0.6646344010569859
        }
    ],
    "Goal left crossbar": [
        {
            "x": 0.40964344854411866,
            "y": 0.2942535458453468
        },
        {
            "x": 0.22405155940228527,
            "y": 0.33546783328759194
        }
    ],
    "Small rect. left top": [
        {
            "x": 0.7289667226446876,
            "y": 0.4597373016488372
        },
        {
            "x": 0.5600435658967404,
            "y": 0.44230770536445696
        },
        {
            "x": 0.6564627476897473,
            "y": 0.45143783306945345
        },
        {
            "x": 0.6039506918422681,
            "y": 0.44660230945711277
        }
    ],
    "Small rect. left bottom": [
        {
            "x": 0.2544094223648632,
            "y": 0.6221248316561934
        },
        {
            "x": 0.052738898284455375,
            "y": 0.5952300111186387
        },
        {
            "x": 0.11466389103829928,
            "y": 0.6033845500965753
        },
        {
            "x": 0.1849448530671526,
            "y": 0.6123104954400735
        }
    ],
    "Big rect. left bottom": [
        {
            "x": 0.3551149382149911,
            "y": 0.8586988759665342
        },
        {
            "x": 0.0016006005335493267,
            "y": 0.7957705419834383
        },
        {
            "x": 0.10130677966687479,
            "y": 0.8131392656355292
        },
        {
            "x": 0.19803539106468623,
            "y": 0.8295302627228982
        },
        {
            "x": 0.2750515154034029,
            "y": 0.8432297347962818
        }
    ],
    "Goal left post left ": [
        {
            "x": 0.21884744998607059,
            "y": 0.5377652982173751
        },
        {
            "x": 0.2156112741290483,
            "y": 0.34665010903651733
        }
    ],
    "Big rect. left top": [
        {
            "x": 0.7913519174254473,
            "y": 0.37194955505331334
        },
        {
            "x": 1.0025390625,
            "y": 0.3905277777777778
        },
        {
            "x": 0.8561068388710907,
            "y": 0.3763300596452663
        },
        {
            "x": 0.9284780056832069,
            "y": 0.38236979547588834
        },
        {
            "x": 0.9982631570445236,
            "y": 0.3884545719223243
        }
    ]
}