{
    "Circle right": [
        {
            "x": 0.07416625155070347,
            "y": 0.6368896030960993
        },
        {
            "x": 0.3532641786599213,
            "y": 0.7042546162158514
        },
        {
            "x": 0.07208673971436967,
            "y": 0.5099980727832305
        },
        {
            "x": 0.029582991803278686,
            "y": 0.5859683515482694
        },
        {
            "x": 0.20768509676424526,
            "y": 0.6848229453397919
        },
        {
            "x": 0.046089442104287066,
            "y": 0.5320076446105569
        },
        {
            "x": 0.04344953893442623,
            "y": 0.6124624316939891
        },
        {
            "x": 0.2795710752682681,
            "y": 0.6978798358011361
        },
        {
            "x": 0.03013101946721311,
            "y": 0.5582297358834244
        },
        {
            "x": 0.1299064218421118,
            "y": 0.6624060826599035
        }
    ],
    "Big rect. right bottom": [
        {
            "x": 0.9967952842042812,
            "y": 0.8550772247373973
        },
        {
            "x": 0.6908791182588347,
            "y": 0.938713447440518
        },
        {
            "x": 0.7924194173522077,
            "y": 0.9097842219574106
        },
        {
            "x": 0.9043126829309073,
            "y": 0.8796872517053899
        }
    ],
    "Goal right post left": [
        {
            "x": 0.6653807894155467,
            "y": 0.3024724364975641
        },
        {
            "x": 0.6635804507910378,
            "y": 0.4426094947264153
        }
    ],
    "Small rect. right main": [
        {
            "x": 0.7867062787288759,
            "y": 0.6357228084219121
        },
        {
            "x": 0.4084554329198732,
            "y": 0.4279550594242952
        },
        {
            "x": 0.6171706292168542,
            "y": 0.5415930366736021
        },
        {
            "x": 0.6951714960745773,
            "y": 0.5847398001901314
        },
        {
            "x": 0.47024124395533234,
            "y": 0.46169804971231454
        },
        {
            "x": 0.5383065187825159,
            "y": 0.4985083436315528
        }
    ],
    "Side line right": [
        {
            "x": 0.9980277508224988,
            "y": 0.6114093475408547
        },
        {
            "x": 0.17662408564420776,
            "y": 0.2053184311746787
        },
        {
            "x": 0.24920160168816846,
            "y": 0.24122409927494248
        },
        {
            "x": 0.3444778299635579,
            "y": 0.290181073426132
        },
        {
            "x": 0.43517122744673886,
            "y": 0.33533394622300655
        },
        {
            "x": 0.520380070185911,
            "y": 0.3774239207900864
        },
        {
            "x": 0.6335786543927484,
            "y": 0.4333374910019561
        },
        {
            "x": 0.7578560519883096,
            "y": 0.4946068326225035
        },
        {
            "x": 0.8577085917706685,
            "y": 0.5423506531806618
        }
    ],
    "Big rect. right top": [
        {
            "x": 0.36643914205516603,
            "y": 0.30546903030091627
        },
        {
            "x": 0.00250093833367082,
            "y": 0.3597252105306602
        },
        {
            "x": 0.1133908888639417,
            "y": 0.3430833972590011
        },
        {
            "x": 0.23236257127176485,
            "y": 0.3256999268248975
        }
    ],
    "Goal right crossbar": [
        {
            "x": 0.6709381026107214,
            "y": 0.2959956129168973
        },
        {
            "x": 0.8198109503590942,
            "y": 0.35706117312564967
        }
    ],
    "Goal right post right": [
        {
            "x": 0.8303475948113075,
            "y": 0.3779926715306124
        },
        {
            "x": 0.8290474620273347,
            "y": 0.5246240685061995
        }
    ],
    "Small rect. right bottom": [
        {
            "x": 0.9631591479263575,
            "y": 0.5983971699511265
        },
        {
            "x": 0.7929568855955739,
            "y": 0.6379260056379403
        },
        {
            "x": 0.8623574579312017,
            "y": 0.6214973643037968
        },
        {
            "x": 0.9211147971859895,
            "y": 0.6073932948130772
        }
    ],
    "Side line top": [
        {
            "x": 0.17173984077327065,
            "y": 0.20543456907722643
        },
        {
            "x": 0.0020183140133318202,
            "y": 0.2241898268818961
        },
        {
            "x": 0.08136982436600328,
            "y": 0.2158298052886004
        }
    ],
    "Big rect. right main": [
        {
            "x": 0.001805861768447492,
            "y": 0.4599037593764247
        },
        {
            "x": 0.6849035017407098,
            "y": 0.9383830272268165
        },
        {
            "x": 0.06557365639816491,
            "y": 0.5021283019312761
        },
        {
            "x": 0.5640509523262773,
            "y": 0.8498274329825364
        },
        {
            "x": 0.13817094270639863,
            "y": 0.5512643752878866
        },
        {
            "x": 0.2312004913942657,
            "y": 0.6148687418147699
        },
        {
            "x": 0.33594355710797963,
            "y": 0.687524587615483
        },
        {
            "x": 0.43753382217018183,
            "y": 0.7596919045693474
        }
    ],
    "Small rect. right top": [
        {
            "x": 0.40944964732102135,
            "y": 0.42401663425940006
        },
        {
            "x": 0.5544364122118294,
            "y": 0.39797102671789697
        },
        {
            "x": 0.5132417357768122,
            "y": 0.40602323839073096
        },
        {
            "x": 0.4689175322241196,
            "y": 0.41362064756994943
        }
    ]
}