{
    "Circle right": [
        {
            "x": 0.1231493445306935,
            "y": 0.5157813642907535
        },
        {
            "x": 0.024167053934030895,
            "y": 0.4936640069511185
        },
        {
            "x": 0.07530552144536336,
            "y": 0.502248252200029
        },
        {
            "x": 0.21875071752032504,
            "y": 0.5627154073743708
        },
        {
            "x": 0.16778844921501895,
            "y": 0.5337467189590335
        }
    ],
    "Big rect. right main": [
        {
            "x": 0.0051539607552000075,
            "y": 0.6041779842843045
        },
        {
            "x": 0.8238587838787778,
            "y": 0.4685664026965524
        },
        {
            "x": 0.33580963023660776,
            "y": 0.5491576933694549
        },
        {
            "x": 0.48522184493387566,
            "y": 0.5240963092601126
        },
        {
            "x": 0.6643248821417214,
            "y": 0.4935325903302207
        },
        {
            "x": 0.18281812732721137,
            "y": 0.5743107431098219
        }
    ],
    "Big rect. right top": [
        {
            "x": 0.8321503024728083,
            "y": 0.47087141008172617
        },
        {
            "x": 0.9962918774758343,
            "y": 0.792731076756131
        },
        {
            "x": 0.8804422710980658,
            "y": 0.5669720697629312
        },
        {
            "x": 0.9250586966965224,
            "y": 0.6542027657676691
        },
        {
            "x": 0.9558505485446885,
            "y": 0.7144505831880218
        }
    ]
}