{
    "Goal left crossbar": [
        {
            "x": 0.7065997146655139,
            "y": 0.22474873954710956
        },
        {
            "x": 0.5875860827518053,
            "y": 0.26497897419497696
        }
    ],
    "Small rect. left top": [
        {
            "x": 0.8241975499803387,
            "y": 0.3216054938485737
        },
        {
            "x": 0.9526173756470991,
            "y": 0.34360505466001134
        },
        {
            "x": 0.8693900641209017,
            "y": 0.32826350195725695
        },
        {
            "x": 0.912655558561709,
            "y": 0.3365962087133512
        }
    ],
    "Small rect. left bottom": [
        {
            "x": 0.6045955931454832,
            "y": 0.4958366395175733
        },
        {
            "x": 0.46780009332094263,
            "y": 0.45976797260360663
        },
        {
            "x": 0.518877688355147,
            "y": 0.47214847397978044
        },
        {
            "x": 0.5621455369890707,
            "y": 0.4838368989319456
        }
    ],
    "Side line left": [
        {
            "x": 0.0013156417272088923,
            "y": 0.6372045386960773
        },
        {
            "x": 0.9985932564218118,
            "y": 0.2522562077627946
        }
    ],
    "Goal left post left ": [
        {
            "x": 0.5764043336294248,
            "y": 0.3983873831179854
        },
        {
            "x": 0.575680542906251,
            "y": 0.28166195653659165
        }
    ],
    "Big rect. left main": [
        {
            "x": 0.7058485306171076,
            "y": 0.7417330846711235
        },
        {
            "x": 0.9991223997724159,
            "y": 0.5792049580539138
        },
        {
            "x": 0.9127588433067171,
            "y": 0.6275608733017853
        },
        {
            "x": 0.8061667362270154,
            "y": 0.6858081624156475
        }
    ],
    "Goal left post right": [
        {
            "x": 0.7218442110294638,
            "y": 0.34326645922944576
        },
        {
            "x": 0.7221989341578484,
            "y": 0.2389399733578173
        }
    ],
    "Small rect. left main": [
        {
            "x": 0.6148117278614424,
            "y": 0.49574566065383174
        },
        {
            "x": 0.9567512119146216,
            "y": 0.34961205743159546
        },
        {
            "x": 0.7480342899888913,
            "y": 0.43795034260647414
        },
        {
            "x": 0.6835691445764146,
            "y": 0.46524900787225687
        },
        {
            "x": 0.9013441062780597,
            "y": 0.3730370511800913
        },
        {
            "x": 0.813272792072748,
            "y": 0.41076220308792666
        }
    ],
    "Big rect. left bottom": [
        {
            "x": 0.6940628313040602,
            "y": 0.7418510044572586
        },
        {
            "x": 0.18634869245559343,
            "y": 0.5698194444444444
        },
        {
            "x": 0.15216769368286798,
            "y": 0.5784359766624698
        },
        {
            "x": 0.9048647273976886,
            "y": 0.2867138344573225
        },
        {
            "x": 0.3499883302628402,
            "y": 0.5016613965949482
        },
        {
            "x": 0.3018031391408307,
            "y": 0.6082798042709625
        },
        {
            "x": 0.5220507679181722,
            "y": 0.4346061384027378
        },
        {
            "x": 0.4381131432209001,
            "y": 0.6542690121792126
        },
        {
            "x": 0.6531271294625096,
            "y": 0.3829972893330828
        },
        {
            "x": 0.554668224302823,
            "y": 0.6936652826905694
        },
        {
            "x": 0.7749656785496302,
            "y": 0.33684746932209236
        }
    ],
    "Side line bottom": [
        {
            "x": 0.0024333454057337742,
            "y": 0.893482032744628
        },
        {
            "x": 0.16926295434690644,
            "y": 0.9643467159759379
        },
        {
            "x": 0.24460447945543354,
            "y": 0.9986578099781451
        },
        {
            "x": 0.09392417834951937,
            "y": 0.9315980841412829
        }
    ]
}