{
    "Circle right": [
        {
            "x": 0.5593546357873603,
            "y": 0.4664452631583893
        },
        {
            "x": 0.7830526603603147,
            "y": 0.5288199707710951
        },
        {
            "x": 0.5349641485038044,
            "y": 0.44265671280485736
        },
        {
            "x": 0.7104277997061265,
            "y": 0.5192835193829325
        },
        {
            "x": 0.5414487827133551,
            "y": 0.39709752586435004
        },
        {
            "x": 0.559347951848451,
            "y": 0.38191265016125897
        },
        {
            "x": 0.5978152131643154,
            "y": 0.48729157470493334
        },
        {
            "x": 0.6518782278170212,
            "y": 0.5058672152532433
        },
        {
            "x": 0.5298427377267684,
            "y": 0.41693715728516695
        }
    ],
    "Big rect. right main": [
        {
            "x": 0.9986592278661489,
            "y": 0.6669497028208091
        },
        {
            "x": 0.4146725852815228,
            "y": 0.28605206585656706
        },
        {
            "x": 0.4919098960219033,
            "y": 0.33476827858093483
        },
        {
            "x": 0.5973074524445099,
            "y": 0.4015273521773632
        },
        {
            "x": 0.6850051257477148,
            "y": 0.4582228894466391
        },
        {
            "x": 0.7946634159967378,
            "y": 0.5320742732864617
        },
        {
            "x": 0.8803420881180916,
            "y": 0.5893024568185844
        }
    ],
    "Side line top": [
        {
            "x": 0.002372511770590428,
            "y": 0.22365887520683508
        },
        {
            "x": 0.6416122186721687,
            "y": 0.15836390177660728
        },
        {
            "x": 0.17912305010112226,
            "y": 0.2092681155586522
        },
        {
            "x": 0.3847952668753972,
            "y": 0.18872522664869734
        },
        {
            "x": 0.5173054441996746,
            "y": 0.17388965353525046
        }
    ],
    "Small rect. right main": [
        {
            "x": 0.8447250809667028,
            "y": 0.3237816758013458
        },
        {
            "x": 0.9984767697769937,
            "y": 0.397126396623511
        },
        {
            "x": 0.8852127522283304,
            "y": 0.34350723932378563
        },
        {
            "x": 0.9292463271370656,
            "y": 0.36405152145986686
        },
        {
            "x": 0.9641248602390403,
            "y": 0.3806435572963352
        }
    ],
    "Big rect. right top": [
        {
            "x": 0.41841235138041794,
            "y": 0.28137664676980667
        },
        {
            "x": 0.8071628453779788,
            "y": 0.23093941939455587
        },
        {
            "x": 0.5308640060692882,
            "y": 0.26752126035431806
        },
        {
            "x": 0.6410050028453085,
            "y": 0.2534743001391071
        },
        {
            "x": 0.7198398533686172,
            "y": 0.24258900485868673
        }
    ],
    "Side line right": [
        {
            "x": 0.65187618288047,
            "y": 0.16030980760046978
        },
        {
            "x": 0.9991485422383188,
            "y": 0.30833455855056013
        },
        {
            "x": 0.7520661227384324,
            "y": 0.20377368260437678
        },
        {
            "x": 0.8501216135331662,
            "y": 0.2457797449334423
        },
        {
            "x": 0.9137946192223161,
            "y": 0.272142016654065
        }
    ],
    "Small rect. right top": [
        {
            "x": 0.8464723645998785,
            "y": 0.319204232656189
        },
        {
            "x": 0.971957167672475,
            "y": 0.30129282082484965
        },
        {
            "x": 0.8904919334300097,
            "y": 0.31211587379888567
        },
        {
            "x": 0.9305140541552622,
            "y": 0.30621179012512806
        }
    ]
}