{
    "Small rect. left top": [
        {
            "x": 0.4743860238746491,
            "y": 0.4285169864867905
        },
        {
            "x": 0.6115832602211023,
            "y": 0.45055385958587796
        },
        {
            "x": 0.5169324998576874,
            "y": 0.43597814644276706
        },
        {
            "x": 0.5673001789012446,
            "y": 0.4449289976057891
        }
    ],
    "Goal left crossbar": [
        {
            "x": 0.1915709124675152,
            "y": 0.3650715820613579
        },
        {
            "x": 0.3387718297008454,
            "y": 0.3177048956322363
        }
    ],
    "Circle left": [
        {
            "x": 0.8482169629426173,
            "y": 0.6830707511320016
        },
        {
            "x": 0.9744368469893951,
            "y": 0.5345432218977402
        },
        {
            "x": 0.9352838473271637,
            "y": 0.6603847763645774
        },
        {
            "x": 0.9916318713049117,
            "y": 0.6304799263995936
        },
        {
            "x": 0.9981407735140714,
            "y": 0.5525820794669537
        },
        {
            "x": 0.6724291573456485,
            "y": 0.699854604020367
        },
        {
            "x": 0.7567996371747502,
            "y": 0.6950628470787231
        }
    ],
    "Big rect. left main": [
        {
            "x": 0.32183309999380993,
            "y": 0.8979201493372949
        },
        {
            "x": 0.9985094386327538,
            "y": 0.5169673281163499
        },
        {
            "x": 0.4362505208658385,
            "y": 0.8315281145648576
        },
        {
            "x": 0.5684142187985486,
            "y": 0.7547493413739104
        },
        {
            "x": 0.6855128551539769,
            "y": 0.6890319378811733
        },
        {
            "x": 0.7971381094112714,
            "y": 0.6278038192856098
        },
        {
            "x": 0.9076829657360057,
            "y": 0.5676789356240286
        }
    ],
    "Small rect. left bottom": [
        {
            "x": 0.21454825219530108,
            "y": 0.6338207727730417
        },
        {
            "x": 0.041733266479535736,
            "y": 0.5975858670943943
        },
        {
            "x": 0.09109118985573149,
            "y": 0.6087301880011243
        },
        {
            "x": 0.1536299354836982,
            "y": 0.6216352778739374
        }
    ],
    "Side line top": [
        {
            "x": 0.8752836108953135,
            "y": 0.2645012057357409
        },
        {
            "x": 0.9976058320344321,
            "y": 0.27674866556809125
        },
        {
            "x": 0.9295992807796324,
            "y": 0.2701986037068441
        }
    ],
    "Small rect. left main": [
        {
            "x": 0.22491475825414317,
            "y": 0.6322539564217412
        },
        {
            "x": 0.6046970941303649,
            "y": 0.4642924363895334
        },
        {
            "x": 0.538424365111189,
            "y": 0.49378234389623504
        },
        {
            "x": 0.4664150944055675,
            "y": 0.5256962399923081
        },
        {
            "x": 0.3931200400708245,
            "y": 0.5577861515445758
        },
        {
            "x": 0.31686760534226094,
            "y": 0.5921483451857378
        }
    ],
    "Goal left post right": [
        {
            "x": 0.3576708066336798,
            "y": 0.46332399143626335
        },
        {
            "x": 0.3556970517396737,
            "y": 0.333841106130467
        }
    ],
    "Goal left post left ": [
        {
            "x": 0.18448535186701323,
            "y": 0.5328054674236757
        },
        {
            "x": 0.18196309143481226,
            "y": 0.3866043102731088
        }
    ],
    "Big rect. left bottom": [
        {
            "x": 0.0019432966781901659,
            "y": 0.8235997934934731
        },
        {
            "x": 0.31208982628964405,
            "y": 0.8992212053487104
        },
        {
            "x": 0.08600633723533643,
            "y": 0.843380147220688
        },
        {
            "x": 0.1695330383815838,
            "y": 0.8629734235856803
        },
        {
            "x": 0.24348879905802037,
            "y": 0.881502018568828
        }
    ],
    "Side line left": [
        {
            "x": 0.0018250090543003284,
            "y": 0.6112429896982183
        },
        {
            "x": 0.8701471326524423,
            "y": 0.26571350646899555
        },
        {
            "x": 0.15947521592836286,
            "y": 0.5496788407017075
        },
        {
            "x": 0.29789986885008757,
            "y": 0.49488263621069645
        },
        {
            "x": 0.44519052944814597,
            "y": 0.4369295403860119
        },
        {
            "x": 0.5938230136183463,
            "y": 0.3783007408330256
        },
        {
            "x": 0.7535742370583661,
            "y": 0.31340232491324954
        }
    ],
    "Big rect. left top": [
        {
            "x": 0.6697947714363395,
            "y": 0.3504138626788488
        },
        {
            "x": 0.9980278964767837,
            "y": 0.39363846304467087
        },
        {
            "x": 0.7571261974188195,
            "y": 0.36231342998324817
        },
        {
            "x": 0.8527682335004232,
            "y": 0.3753998292461268
        },
        {
            "x": 0.930490229484622,
            "y": 0.3849741153355692
        }
    ]
}