{
    "Goal right crossbar": [
        {
            "x": 0.7254497041610752,
            "y": 0.2487020547286114
        },
        {
            "x": 0.9422350540799037,
            "y": 0.2793095429803207
        }
    ],
    "Side line top": [
        {
            "x": 0.0009885465710793415,
            "y": 0.2844574100901631
        },
        {
            "x": 0.02600569559030295,
            "y": 0.28330463231238523
        }
    ],
    "Small rect. right top": [
        {
            "x": 0.4069283390969172,
            "y": 0.41974052374931853
        },
        {
            "x": 0.5491456231364578,
            "y": 0.3995160226448541
        },
        {
            "x": 0.45490160481748076,
            "y": 0.41420150390997507
        },
        {
            "x": 0.5061061613663709,
            "y": 0.40662664372903123
        }
    ],
    "Small rect. right main": [
        {
            "x": 0.9693613410137006,
            "y": 0.5602949862681619
        },
        {
            "x": 0.4047447083719975,
            "y": 0.42421183842215077
        },
        {
            "x": 0.5756942541528552,
            "y": 0.46682321140823907
        },
        {
            "x": 0.6854231347833512,
            "y": 0.4924685256369484
        },
        {
            "x": 0.778405325656509,
            "y": 0.5145523511729647
        },
        {
            "x": 0.8712084118338403,
            "y": 0.5369199680314567
        },
        {
            "x": 0.4829083634265739,
            "y": 0.4439484408768158
        }
    ],
    "Circle right": [
        {
            "x": 0.040495330750434606,
            "y": 0.5665518442904673
        },
        {
            "x": 0.36391301597100423,
            "y": 0.6221139793263735
        },
        {
            "x": 0.0028343175605288545,
            "y": 0.5404798202559706
        },
        {
            "x": 0.005051845768315257,
            "y": 0.507019456255226
        },
        {
            "x": 0.22966446918129352,
            "y": 0.6099974216387752
        },
        {
            "x": 0.025887649419657724,
            "y": 0.490729790340365
        },
        {
            "x": 0.1290332415820532,
            "y": 0.5932870101876236
        },
        {
            "x": 0.4727057993005614,
            "y": 0.6278804502902254
        }
    ],
    "Goal right post right": [
        {
            "x": 0.9521667540049122,
            "y": 0.474075821401076
        },
        {
            "x": 0.9553168936028571,
            "y": 0.29595865304360736
        }
    ],
    "Big rect. right main": [
        {
            "x": 0.9982339994845406,
            "y": 0.7955904926340963
        },
        {
            "x": 0.002674087466192022,
            "y": 0.47982261554954525
        },
        {
            "x": 0.10561259458811327,
            "y": 0.510340605345329
        },
        {
            "x": 0.6857863730528887,
            "y": 0.6929014581720145
        },
        {
            "x": 0.23182370096283964,
            "y": 0.5486379336194751
        },
        {
            "x": 0.8251297511516699,
            "y": 0.7370731870308239
        },
        {
            "x": 0.3501351773269029,
            "y": 0.5846162804247185
        },
        {
            "x": 0.4462271721639279,
            "y": 0.6154165645358326
        },
        {
            "x": 0.5646463491406633,
            "y": 0.6541269944391009
        }
    ],
    "Small rect. right bottom": [
        {
            "x": 0.9789109339808684,
            "y": 0.5614974614793323
        },
        {
            "x": 0.9989702688123357,
            "y": 0.55679428598241
        }
    ],
    "Side line right": [
        {
            "x": 0.038552632838617706,
            "y": 0.2836037050450815
        },
        {
            "x": 0.998444762522481,
            "y": 0.49274752222888335
        },
        {
            "x": 0.5234480754235895,
            "y": 0.39061316029672
        },
        {
            "x": 0.6786613240429091,
            "y": 0.42552626266564975
        },
        {
            "x": 0.15545627450101,
            "y": 0.3101068095923582
        },
        {
            "x": 0.836193355570567,
            "y": 0.458700679576642
        },
        {
            "x": 0.2664876948840108,
            "y": 0.3347496737680693
        },
        {
            "x": 0.39395184406290445,
            "y": 0.36290318085944445
        }
    ],
    "Goal right post left": [
        {
            "x": 0.7145097065912935,
            "y": 0.27154951825018464
        },
        {
            "x": 0.7133323820664552,
            "y": 0.42347541412025663
        }
    ],
    "Big rect. right top": [
        {
            "x": 0.2945563685533393,
            "y": 0.3436321986628224
        },
        {
            "x": 0.000844911599213116,
            "y": 0.3727957766765348
        },
        {
            "x": 0.09165242888389898,
            "y": 0.3645571140041554
        },
        {
            "x": 0.18652111393566356,
            "y": 0.354759174883493
        }
    ]
}