{
    "Side line bottom": [
        {
            "x": 0.5119435975732779,
            "y": 0.9946105905458191
        },
        {
            "x": 0.9970984293986631,
            "y": 0.7718047846572638
        },
        {
            "x": 0.6202839581143468,
            "y": 0.9421075376911974
        },
        {
            "x": 0.7393152378849318,
            "y": 0.8867274948917597
        },
        {
            "x": 0.8397125687246202,
            "y": 0.8416148399837678
        },
        {
            "x": 0.9232455997645282,
            "y": 0.80380117276573
        }
    ],
    "Goal right crossbar": [
        {
            "x": 0.4118862944379767,
            "y": 0.2705551632304216
        },
        {
            "x": 0.3042352645248881,
            "y": 0.23849424669510785
        }
    ],
    "Circle right": [
        {
            "x": 0.02627697072926801,
            "y": 0.534044807314905
        },
        {
            "x": 0.00258393410614939,
            "y": 0.5321652885434393
        },
        {
            "x": 0.054554592071050484,
            "y": 0.5337747894693396
        }
    ],
    "Big rect. right main": [
        {
            "x": 0.3293751992765487,
            "y": 0.669893560352315
        },
        {
            "x": 0.00936024560368446,
            "y": 0.5068953752767322
        },
        {
            "x": 0.06949835600071515,
            "y": 0.5374670159033483
        },
        {
            "x": 0.1308011282209162,
            "y": 0.5678536518592591
        },
        {
            "x": 0.19628577200192787,
            "y": 0.6014147684478122
        },
        {
            "x": 0.2592920202359466,
            "y": 0.6335145492750335
        }
    ],
    "Small rect. right main": [
        {
            "x": 0.3938539849181882,
            "y": 0.4675533323830991
        },
        {
            "x": 0.09224512235957066,
            "y": 0.3491449084563753
        },
        {
            "x": 0.1501720232353662,
            "y": 0.37132264300963574
        },
        {
            "x": 0.21081049752632042,
            "y": 0.39434479468757716
        },
        {
            "x": 0.2768729410447062,
            "y": 0.4206293910957952
        },
        {
            "x": 0.33619563577569833,
            "y": 0.444076556112719
        }
    ],
    "Side line right": [
        {
            "x": 0.9969115650385451,
            "y": 0.6056660273767831
        },
        {
            "x": 0.0031202088112917835,
            "y": 0.2514758394692392
        },
        {
            "x": 0.07751076497386168,
            "y": 0.2777647126377893
        },
        {
            "x": 0.15612088841536606,
            "y": 0.30503306105949973
        },
        {
            "x": 0.24786107372955798,
            "y": 0.33740264789873536
        },
        {
            "x": 0.34425239741578906,
            "y": 0.3712148509104897
        },
        {
            "x": 0.43344963327205405,
            "y": 0.4030726129707035
        },
        {
            "x": 0.536168774659729,
            "y": 0.4410206199772876
        },
        {
            "x": 0.6551707402180448,
            "y": 0.4839243401485761
        },
        {
            "x": 0.7839344029494012,
            "y": 0.5301948848419953
        },
        {
            "x": 0.8809334617774336,
            "y": 0.5644361337322413
        }
    ],
    "Small rect. right top": [
        {
            "x": 0.20347000088405365,
            "y": 0.3245416666666667
        },
        {
            "x": 0.09519250090589432,
            "y": 0.3439328038730386
        },
        {
            "x": 0.1327877956398719,
            "y": 0.33787204442518765
        },
        {
            "x": 0.17021871185865228,
            "y": 0.33077299957240036
        }
    ],
    "Big rect. right bottom": [
        {
            "x": 0.7645633471741721,
            "y": 0.5268129116288566
        },
        {
            "x": 0.338068318340856,
            "y": 0.6712142969870147
        },
        {
            "x": 0.42569577820556387,
            "y": 0.6408452599066525
        },
        {
            "x": 0.5248131126555866,
            "y": 0.6066444021595054
        },
        {
            "x": 0.6031866212641552,
            "y": 0.5800193271294011
        },
        {
            "x": 0.6862575588640286,
            "y": 0.5528856983447451
        }
    ],
    "Goal right post left": [
        {
            "x": 0.29527998018748536,
            "y": 0.24944456319362082
        },
        {
            "x": 0.29559375000000004,
            "y": 0.3464344190079733
        }
    ],
    "Small rect. right bottom": [
        {
            "x": 0.5198153965454407,
            "y": 0.43756897604712375
        },
        {
            "x": 0.40152534192061173,
            "y": 0.46807892404026913
        },
        {
            "x": 0.4461310930092298,
            "y": 0.456784530771399
        },
        {
            "x": 0.4845682546234255,
            "y": 0.4466702652430285
        }
    ],
    "Big rect. right top": [
        {
            "x": 0.002423558868398962,
            "y": 0.2770178356724769
        },
        {
            "x": 0.04620970213793932,
            "y": 0.27082942105634433
        },
        {
            "x": 0.024632728907907717,
            "y": 0.2736987581027007
        }
    ],
    "Goal right post right": [
        {
            "x": 0.4226315610888429,
            "y": 0.2839940511695381
        },
        {
            "x": 0.4225502822138071,
            "y": 0.3918305188477829
        }
    ]
}