{
    "Goal right crossbar": [
        {
            "x": 0.765333323848735,
            "y": 0.3600277078907661
        },
        {
            "x": 0.6487557586212197,
            "y": 0.2803162550844406
        }
    ],
    "Small rect. right main": [
        {
            "x": 0.40284749718469465,
            "y": 0.38272287222937496
        },
        {
            "x": 0.7120327385953,
            "y": 0.6458482760510159
        },
        {
            "x": 0.45320508546163124,
            "y": 0.4251363372859279
        },
        {
            "x": 0.5047492821526892,
            "y": 0.46920995662141207
        },
        {
            "x": 0.5664786170932652,
            "y": 0.5208230282145914
        },
        {
            "x": 0.6170645134981396,
            "y": 0.5639761599408555
        },
        {
            "x": 0.6610295491457323,
            "y": 0.6015957649870989
        }
    ],
    "Goal right post right": [
        {
            "x": 0.7752745378795302,
            "y": 0.5035726120840018
        },
        {
            "x": 0.7787939864668662,
            "y": 0.3822685299673558
        }
    ],
    "Small rect. right bottom": [
        {
            "x": 0.7191438684741329,
            "y": 0.6479510688438798
        },
        {
            "x": 0.8835465388824143,
            "y": 0.6076198663594633
        },
        {
            "x": 0.8228188207850335,
            "y": 0.6217851248932775
        },
        {
            "x": 0.7698247532750944,
            "y": 0.6346754721456511
        }
    ],
    "Small rect. right top": [
        {
            "x": 0.5472243352624363,
            "y": 0.3505940799611205
        },
        {
            "x": 0.40452993227811396,
            "y": 0.37922884392222783
        },
        {
            "x": 0.4485908881782497,
            "y": 0.37025059018024814
        },
        {
            "x": 0.5004262881184227,
            "y": 0.3600922686116703
        }
    ],
    "Circle right": [
        {
            "x": 0.05775793511460668,
            "y": 0.5041468182090416
        },
        {
            "x": 0.11146918621241705,
            "y": 0.6554977618988702
        },
        {
            "x": 0.07579438226882457,
            "y": 0.6300757364383226
        },
        {
            "x": 0.30182678221558146,
            "y": 0.7119629754312109
        },
        {
            "x": 0.15291527406069713,
            "y": 0.6764851936302861
        },
        {
            "x": 0.04957888683480587,
            "y": 0.5990443366288172
        },
        {
            "x": 0.24704326576748514,
            "y": 0.7042114993314472
        },
        {
            "x": 0.037449954561742355,
            "y": 0.5541831096173807
        },
        {
            "x": 0.19433285031171652,
            "y": 0.6912672660772299
        },
        {
            "x": 0.08451704072633745,
            "y": 0.47543454899006093
        }
    ],
    "Big rect. right main": [
        {
            "x": 0.0012646191883378581,
            "y": 0.38524266408521574
        },
        {
            "x": 0.5590162765375306,
            "y": 0.9970458565371997
        },
        {
            "x": 0.06004865979029128,
            "y": 0.4459735825147029
        },
        {
            "x": 0.1302874363308794,
            "y": 0.519510879750995
        },
        {
            "x": 0.1991296480567552,
            "y": 0.5931685597784869
        },
        {
            "x": 0.2821266995954104,
            "y": 0.6832411546499736
        },
        {
            "x": 0.35046935182056593,
            "y": 0.7583565726648078
        },
        {
            "x": 0.42303700777199243,
            "y": 0.840598793922513
        },
        {
            "x": 0.49020499942352025,
            "y": 0.9174919995630457
        }
    ],
    "Side line right": [
        {
            "x": 0.2314835217361865,
            "y": 0.11045466601383462
        },
        {
            "x": 0.9988808166736027,
            "y": 0.6921656189122299
        },
        {
            "x": 0.2762721748900728,
            "y": 0.14505476287484165
        },
        {
            "x": 0.33755225545079426,
            "y": 0.19048280868521675
        },
        {
            "x": 0.4012038839776837,
            "y": 0.23826260791953766
        },
        {
            "x": 0.4563549215229495,
            "y": 0.27923754921990684
        },
        {
            "x": 0.5114061306021757,
            "y": 0.3205566469362603
        },
        {
            "x": 0.5758138380942095,
            "y": 0.3691505420595223
        },
        {
            "x": 0.65372124427084,
            "y": 0.4286094551801574
        },
        {
            "x": 0.7275061900363379,
            "y": 0.48480422923400296
        },
        {
            "x": 0.7928651417994129,
            "y": 0.5347532651085484
        },
        {
            "x": 0.897085888908123,
            "y": 0.613696699074067
        }
    ],
    "Goal right post left": [
        {
            "x": 0.6394057900351459,
            "y": 0.4048445128660943
        },
        {
            "x": 0.6417912201982304,
            "y": 0.29172550576337986
        }
    ],
    "Big rect. right top": [
        {
            "x": 0.391179598953454,
            "y": 0.23366354062182604
        },
        {
            "x": 0.00081111513524459,
            "y": 0.30069444444444443
        },
        {
            "x": 0.09542085872520786,
            "y": 0.285877216626077
        },
        {
            "x": 0.20344847605944874,
            "y": 0.2672368321855833
        },
        {
            "x": 0.29416560839090866,
            "y": 0.250207244075535
        }
    ],
    "Big rect. right bottom": [
        {
            "x": 0.9982971899417791,
            "y": 0.8683876008127854
        },
        {
            "x": 0.5688781514080488,
            "y": 0.9984488181185506
        },
        {
            "x": 0.6711592727508343,
            "y": 0.9651886374969977
        },
        {
            "x": 0.7893066466368368,
            "y": 0.9292948588263746
        },
        {
            "x": 0.90378971091829,
            "y": 0.8954124292693568
        }
    ],
    "Side line top": [
        {
            "x": 0.22530243983327272,
            "y": 0.1078888888888889
        },
        {
            "x": 0.0010645886150085235,
            "y": 0.13950926261270383
        },
        {
            "x": 0.10484711264792619,
            "y": 0.12551106107757076
        }
    ]
}