{
    "Big rect. left bottom": [
        {
            "x": 0.9798371346315878,
            "y": 0.8038825782024276
        },
        {
            "x": 0.4238402376806636,
            "y": 0.6931998055658736
        },
        {
            "x": 0.7704884364143842,
            "y": 0.7606615681949372
        },
        {
            "x": 0.8794750752515093,
            "y": 0.7826116117067664
        },
        {
            "x": 0.5110692414125887,
            "y": 0.7089350734904533
        },
        {
            "x": 0.6378775950608702,
            "y": 0.7340304156779511
        }
    ],
    "Small rect. left bottom": [
        {
            "x": 0.5095203521538638,
            "y": 0.4899101541629698
        },
        {
            "x": 0.6537323812002479,
            "y": 0.5116680758632055
        },
        {
            "x": 0.6085831305260904,
            "y": 0.5054300888714396
        },
        {
            "x": 0.5655771206361409,
            "y": 0.49838377319096977
        }
    ],
    "Goal left crossbar": [
        {
            "x": 0.5745309257030193,
            "y": 0.221258605818859
        },
        {
            "x": 0.5422049785089802,
            "y": 0.2899278782648063
        }
    ],
    "Side line top": [
        {
            "x": 0.699151432901912,
            "y": 0.04533996656323413
        },
        {
            "x": 0.9989082177415428,
            "y": 0.06917198900840976
        },
        {
            "x": 0.809492494014873,
            "y": 0.05627338433254844
        },
        {
            "x": 0.909799812164845,
            "y": 0.06412387697158584
        }
    ],
    "Small rect. left main": [
        {
            "x": 0.6592082249952838,
            "y": 0.5087333014313808
        },
        {
            "x": 0.7306465053796506,
            "y": 0.27209864546435086
        },
        {
            "x": 0.6743893004114466,
            "y": 0.4568941958669584
        },
        {
            "x": 0.7140369307094683,
            "y": 0.32636102796402877
        },
        {
            "x": 0.6944470961301468,
            "y": 0.38984892303238683
        }
    ],
    "Small rect. left top": [
        {
            "x": 0.7272195747832793,
            "y": 0.2671057292141218
        },
        {
            "x": 0.6100044522790649,
            "y": 0.2533732731264004
        },
        {
            "x": 0.6963861501896943,
            "y": 0.2640254163902741
        },
        {
            "x": 0.6564131009130753,
            "y": 0.2591310371849594
        }
    ],
    "Goal left post left ": [
        {
            "x": 0.5393828125,
            "y": 0.3926792958460447
        },
        {
            "x": 0.5395846316309957,
            "y": 0.31006239904876964
        }
    ],
    "Side line left": [
        {
            "x": 0.6956869472032284,
            "y": 0.04784264832246718
        },
        {
            "x": 0.292429507910377,
            "y": 0.9967845999917455
        },
        {
            "x": 0.3464134785412979,
            "y": 0.8674575650577884
        },
        {
            "x": 0.4024750933287809,
            "y": 0.7346678949870413
        },
        {
            "x": 0.4556948730862374,
            "y": 0.6080433920784284
        },
        {
            "x": 0.502141355961117,
            "y": 0.4982529721835463
        },
        {
            "x": 0.5456030629945466,
            "y": 0.3947223790325376
        },
        {
            "x": 0.5784782080272515,
            "y": 0.31814678306447153
        },
        {
            "x": 0.6142911728138526,
            "y": 0.23506281754399647
        },
        {
            "x": 0.6466148093731894,
            "y": 0.16109227287491235
        },
        {
            "x": 0.6718982188105306,
            "y": 0.10382603863405446
        }
    ],
    "Big rect. left main": [
        {
            "x": 0.9853903840753903,
            "y": 0.7984352459036189
        },
        {
            "x": 0.9989742663472178,
            "y": 0.4807932241169046
        },
        {
            "x": 0.9903736067793222,
            "y": 0.6777862292192536
        },
        {
            "x": 0.9949285479446347,
            "y": 0.5731038762001773
        }
    ],
    "Big rect. left top": [
        {
            "x": 0.9984587195013447,
            "y": 0.18422710235860656
        },
        {
            "x": 0.6534644580266541,
            "y": 0.15276161767472582
        },
        {
            "x": 0.7486853525213483,
            "y": 0.1617492747782751
        },
        {
            "x": 0.8647563887576959,
            "y": 0.17257738262720362
        }
    ],
    "Goal left post right": [
        {
            "x": 0.5801982443791612,
            "y": 0.3023805556687332
        },
        {
            "x": 0.5808099744360209,
            "y": 0.2267774169780872
        }
    ]
}