{
    "Goal right post left": [
        {
            "x": 0.882031261920929,
            "y": 0.3799305260181427
        },
        {
            "x": 0.8805233836174011,
            "y": 0.5104583501815796
        }
    ],
    "Goal right crossbar": [
        {
            "x": 0.8818437457084656,
            "y": 0.38026389479637146
        },
        {
            "x": 1.0,
            "y": 0.4057638943195343
        }
    ],
    "Side line right": [
        {
            "x": 0.45952343940734863,
            "y": 0.37768054008483887
        },
        {
            "x": 1.0,
            "y": 0.5458611249923706
        }
    ],
    "Side line top": [
        {
            "x": 0.4597812592983246,
            "y": 0.37759721279144287
        },
        {
            "x": 0.0,
            "y": 0.41970834136009216
        }
    ],
    "Big rect. right top": [
        {
            "x": 0.2414843738079071,
            "y": 0.46937501430511475
        },
        {
            "x": 0.6212655901908875,
            "y": 0.43065279722213745
        }
    ],
    "Big rect. right bottom": [
        {
            "x": 0.9546483755111694,
            "y": 0.7978749871253967
        },
        {
            "x": 1.0,
            "y": 0.7908194661140442
        }
    ],
    "Big rect. right main": [
        {
            "x": 0.9544687271118164,
            "y": 0.7981944680213928
        },
        {
            "x": 0.24160155653953552,
            "y": 0.4697639048099518
        }
    ],
    "Small rect. right top": [
        {
            "x": 0.6607500314712524,
            "y": 0.4966111183166504
        },
        {
            "x": 0.7822890877723694,
            "y": 0.4821527600288391
        }
    ],
    "Small rect. right main": [
        {
            "x": 1.0,
            "y": 0.6151805520057678
        },
        {
            "x": 0.6607500314712524,
            "y": 0.49702775478363037
        }
    ],
    "Circle right": [
        {
            "x": 0.3997578024864197,
            "y": 0.5426666736602783
        },
        {
            "x": 0.3792499899864197,
            "y": 0.554444432258606
        },
        {
            "x": 0.36821094155311584,
            "y": 0.5729583501815796
        },
        {
            "x": 0.37073439359664917,
            "y": 0.5813611149787903
        },
        {
            "x": 0.37672656774520874,
            "y": 0.5909028053283691
        },
        {
            "x": 0.39186719059944153,
            "y": 0.6032360792160034
        },
        {
            "x": 0.4155234396457672,
            "y": 0.6144444346427917
        },
        {
            "x": 0.43950000405311584,
            "y": 0.6239861249923706
        },
        {
            "x": 0.4704062342643738,
            "y": 0.6307083368301392
        },
        {
            "x": 0.49879688024520874,
            "y": 0.6385555863380432
        },
        {
            "x": 0.6110859513282776,
            "y": 0.6525833010673523
        },
        {
            "x": 0.6356874704360962,
            "y": 0.6531388759613037
        }
    ]
}